wiki_con/__init__.py
wiki_con/console.py
wiki_con/wikipedia.py
wiki_con-0.1.2.dist-info/entry_points.txt
wiki_con-0.1.2.dist-info/LICENSE
wiki_con-0.1.2.dist-info/WHEEL
wiki_con-0.1.2.dist-info/METADATA
wiki_con-0.1.2.dist-info/RECORD
