Metadata-Version: 2.1
Name: wiki-con
Version: 0.1.2
Summary: A hypermodern Python console project
Home-page: https://github.com/kevinbowen777/wiki-con/
License: MIT
Keywords: hypermodern,wiki-con
Author: Kevin Bowen
Author-email: kevin.bowen@gmail.com
Requires-Python: >=3.8,<4.0
Classifier: License :: OSI Approved :: MIT License
Classifier: Programming Language :: Python :: 3
Classifier: Programming Language :: Python :: 3.10
Classifier: Programming Language :: Python :: 3.8
Classifier: Programming Language :: Python :: 3.9
Requires-Dist: Pygments (>=2.12.0,<3.0.0)
Requires-Dist: click (>=8.1.3,<9.0.0)
Requires-Dist: desert (>=2020.11.18,<2021.0.0)
Requires-Dist: importlib-metadata (>=4.11.4,<5.0.0); python_version < "3.8"
Requires-Dist: marshmallow (>=3.16.0,<4.0.0)
Requires-Dist: requests (>=2.27.1,<3.0.0)
Project-URL: Documentation, https://wiki-con.readthedocs.io/
Project-URL: Repository, https://github.com/kevinbowen777/wiki-con/
